openedxscorm/__about__.py
openedxscorm/__init__.py
openedxscorm/scormxblock.py
openedxscorm/storage.py
openedxscorm/tests.py
openedxscorm/locale/ar/LC_MESSAGES/django.mo
openedxscorm/locale/ar/LC_MESSAGES/django.po
openedxscorm/locale/es_419/LC_MESSAGES/django.mo
openedxscorm/locale/es_419/LC_MESSAGES/django.po
openedxscorm/locale/fr/LC_MESSAGES/django.mo
openedxscorm/locale/fr/LC_MESSAGES/django.po
openedxscorm/locale/pt_PT/LC_MESSAGES/django.mo
openedxscorm/locale/pt_PT/LC_MESSAGES/django.po
openedxscorm/static/css/scormxblock.css
openedxscorm/static/html/popup.html
openedxscorm/static/html/scormxblock.html
openedxscorm/static/html/studio.html
openedxscorm/static/js/src/scorm.js
openedxscorm/static/js/src/scormxblock.js
openedxscorm/static/js/src/studio.js
openedxscorm/static/js/vendor/renderjson.js
openedx_scorm_xblock-19.0.2.dist-info/LICENSE.txt
openedx_scorm_xblock-19.0.2.dist-info/METADATA
openedx_scorm_xblock-19.0.2.dist-info/WHEEL
openedx_scorm_xblock-19.0.2.dist-info/entry_points.txt
openedx_scorm_xblock-19.0.2.dist-info/top_level.txt
openedx_scorm_xblock-19.0.2.dist-info/RECORD
