Metadata-Version: 2.2
Name: openedx-scorm-xblock
Version: 19.0.2
Summary: Scorm XBlock for Open edX
Author: Overhang.IO
Author-email: contact@overhang.io
Maintainer: Edly
Maintainer-email: zia.fazal@edly.io
License: AGPLv3
Project-URL: Documentation, https://github.com/overhangio/openedx-scorm-xblock
Project-URL: Code, https://github.com/overhangio/openedx-scorm-xblock
Project-URL: Issue tracker, https://github.com/overhangio/openedx-scorm-xblock/issues
Project-URL: Community, https://discuss.openedx.com
Classifier: License :: OSI Approved :: GNU Affero General Public License v3
Requires-Python: >=3.8
License-File: LICENSE.txt
Requires-Dist: xblock
Requires-Dist: web-fragments
Dynamic: author
Dynamic: author-email
Dynamic: classifier
Dynamic: description
Dynamic: description-content-type
Dynamic: license
Dynamic: maintainer
Dynamic: maintainer-email
Dynamic: project-url
Dynamic: requires-dist
Dynamic: requires-python
Dynamic: summary
